{
	"format_version": "1.8.0",
	"animations": {
		"land_short_distance": {
			"animation_length": 1,
			"bones": {
				"body": {
					"position": {
						"0.0": {
							"vector": [0, 0, 0]
						},
						"0.25": {
							"vector": [0, -1, 0]
						},
						"0.375": {
							"vector": [0, -1, 0]
						},
						"1.0": {
							"vector": [0, 0, 0]
						}
					}
				},
				"right_arm": {
					"rotation": {
						"0.0": {
							"vector": [0, 0, 0]
						},
						"0.25": {
							"vector": [-32.47528, 1.34295, 2.10886]
						},
						"0.375": {
							"vector": [-32.47528, 1.34295, 2.10886]
						},
						"1.0": {
							"vector": [0, 0, 0]
						}
					}
				},
				"left_arm": {
					"rotation": {
						"0.0": {
							"vector": [0, 0, 0]
						},
						"0.25": {
							"vector": [25.24198, -3.46739, -4.38575]
						},
						"0.375": {
							"vector": [25.24198, -3.46739, -4.38575]
						},
						"1.0": {
							"vector": [0, 0, 0]
						}
					}
				},
				"right_leg": {
					"position": {
						"0.0": {
							"vector": [0, 0, 0]
						},
						"0.25": {
							"vector": [0, 1, -0.25]
						},
						"0.375": {
							"vector": [0, 1, -0.25]
						},
						"1.0": {
							"vector": [0, 0, 0]
						}
					}
				},
				"left_leg": {
					"position": {
						"0.0": {
							"vector": [0, 0, 0]
						},
						"0.25": {
							"vector": [0, 1, 0.25]
						},
						"0.375": {
							"vector": [0, 1, 0.25]
						},
						"1.0": {
							"vector": [0, 0, 0]
						}
					}
				}
			}
		}
	}
}